[
  {
    "consecutivo": 1,
    "fecha": "2026-04-10",
    "tercero": "prueba",
    "identificacion": "74845",
    "productos": "RLAJ 340g x340",
    "domicilio": "",
    "total": 47000.00000000001,
    "forma_pago": "Efectivo",
    "status": "En proceso"
  },
  {
    "consecutivo": 2,
    "fecha": "2026-04-11",
    "tercero": "Juan Felipe Parra Barrera",
    "identificacion": "1020777792",
    "productos": "BSIN 500g x500",
    "domicilio": "Nacional Transportadora",
    "total": 157000,
    "forma_pago": "T. Débito",
    "status": "En proceso",
    "items_molienda": [
      {
        "sku": "BSIN",
        "presentacion": "500g",
        "molienda": "grano"
      }
    ]
  }
]